oasis/__init__.py
oasis/cli.py
oasis/config.py
oasis/exceptions.py
oasis/logger.py
oasis/oasis.py
oasis/app/oasis_app.py
oasis/app/style.css
oasis/models/__init__.py
oasis/models/post.py
oasis/services/ZennAPI_v1.py
oasis/services/ZennAPI_v2.py
oasis/services/__init__.py
oasis/services/file_handler.py
oasis/services/link_preview_generator.py
oasis/services/llm_api.py
oasis/services/markdown_processor.py
oasis/services/note_api_v1.py
oasis/services/note_api_v2.py
oasis/services/qiita_api.py
oasis/services/wordpress_api.py
oasis_article-0.9.2.dist-info/METADATA
oasis_article-0.9.2.dist-info/WHEEL
oasis_article-0.9.2.dist-info/entry_points.txt
oasis_article-0.9.2.dist-info/top_level.txt
oasis_article-0.9.2.dist-info/RECORD
