Metadata-Version: 2.1
Name: oasis-article
Version: 0.9.2
Summary: WordPressへの投稿を自動化するパッケージ
Home-page: https://github.com/Sunwood-ai-labs/OASIS
Author: Sunwood-ai-labs
Author-email: sunwood.ai.labs@gmail.com
Classifier: Development Status :: 3 - Alpha
Classifier: Intended Audience :: Developers
Classifier: License :: OSI Approved :: MIT License
Classifier: Operating System :: OS Independent
Classifier: Programming Language :: Python :: 3
Classifier: Programming Language :: Python :: 3.7
Classifier: Programming Language :: Python :: 3.8
Classifier: Programming Language :: Python :: 3.9
Classifier: Programming Language :: Python :: 3.10
Requires-Python: >=3.7
Requires-Dist: requests
Requires-Dist: python-dotenv
Requires-Dist: matplotlib
Requires-Dist: japanize-matplotlib
Requires-Dist: numpy
Requires-Dist: tenacity
Requires-Dist: litellm
Requires-Dist: loguru
Requires-Dist: click
Requires-Dist: art
Requires-Dist: selenium >=4.12.0
Requires-Dist: janome >=0.5.0
Requires-Dist: markdown
Requires-Dist: beautifulsoup4
Requires-Dist: webdriver-manager
Requires-Dist: mistune
Requires-Dist: html2text
Requires-Dist: streamlit
